Workbook
Name Market_return: assumptions!#REF!

Sheet Sheet1

Sheet assumptions
B1: TESLA, INC. — KEY ASSUMPTIONS
B2: Financial Year | C2: 2023A | D2: 2024A | E2: 2025A | F2: 2026E | G2: 2027E | H2: 2028E | I2: 2029E | J2: 2030E
B4: Revenue Growth Rate | C4: 0.188 | D4: =('income statement'!D5-'income statement'!C5)/'income statement'!C5 -> 0.0094757835 | E4: =('income statement'!E5-'income statement'!D5)/'income statement'!D5 -> -0.029306992 | F4: 0.07 | G4: =F4+1% -> 0.08 | H4: =G4+1% -> 0.09 | I4: =H4+1% -> 0.1 | J4: =I4+1% -> 0.11
B5: COGS % of Sales | C5: ='income statement'!C6/'income statement'!C5 -> 0.81751108 | D5: ='income statement'!D6/'income statement'!D5 -> 0.82137373 | E5: ='income statement'!E6/'income statement'!E5 -> 0.81973489 | F5: =AVERAGE($C5:$E5) -> 0.8195399 | G5: =AVERAGE($C5:$E5) -> 0.8195399 | H5: =AVERAGE($C5:$E5) -> 0.8195399 | I5: =AVERAGE($C5:$E5) -> 0.8195399 | J5: =AVERAGE($C5:$E5) -> 0.8195399
B6: Research And Development Expenses | C6: ='income statement'!C10/'income statement'!C5 -> 0.041013506 | D6: ='income statement'!D10/'income statement'!D5 -> 0.046473539 | E6: ='income statement'!E10/'income statement'!E5 -> 0.067607327 | F6: 0.05 | G6: 0.05 | H6: 0.05 | I6: 0.05 | J6: 0.05
B7: SG&A (Fixed) | C7: ='income statement'!C11/'income statement'!C6 -> 0.060672709 | D7: ='income statement'!D11/'income statement'!D6 -> 0.064182453 | E7: ='income statement'!E11/'income statement'!E6 -> 0.07505178 | F7: =AVERAGE($C7:$E7) -> 0.066635647 | G7: =AVERAGE($C7:$E7) -> 0.066635647 | H7: =AVERAGE($C7:$E7) -> 0.066635647 | I7: =AVERAGE($C7:$E7) -> 0.066635647 | J7: =AVERAGE($C7:$E7) -> 0.066635647
B8: Dep % of Sales | C8: ='income statement'!C15/'income statement'!C5 -> 0.048226261 | D8: ='income statement'!D15/'income statement'!D5 -> 0.05494933 | E8: ='income statement'!E15/'income statement'!E5 -> 0.064833855 | F8: =AVERAGE($C8:$E8) -> 0.056003149 | G8: =AVERAGE($C8:$E8) -> 0.056003149 | H8: =AVERAGE($C8:$E8) -> 0.056003149 | I8: =AVERAGE($C8:$E8) -> 0.056003149 | J8: =AVERAGE($C8:$E8) -> 0.056003149
B9: Total Non-Operating Income/Expense | C9: 1082 | D9: 1914 | E9: 923 | F9: =AVERAGE($C9:$E9) -> 1306.3333 | G9: =AVERAGE($C9:$E9) -> 1306.3333 | H9: =AVERAGE($C9:$E9) -> 1306.3333 | I9: =AVERAGE($C9:$E9) -> 1306.3333 | J9: =AVERAGE($C9:$E9) -> 1306.3333
B10: EBIT MARGIN % | C10: ='income statement'!C14/'income statement'!C5 -> 0.0918748 | D10: ='income statement'!D14/'income statement'!D5 -> 0.072433207 | E10: ='income statement'!E14/'income statement'!E5 -> 0.045925738 | F10: 0.11 | G10: =F10+1.5% -> 0.125 | H10: =G10+1.5% -> 0.14 | I10: =H10+1.5% -> 0.155 | J10: =I10+1.5% -> 0.17
B11: Tax Rate % | C11: ='income statement'!C21/'income statement'!C19 -> -0.50145393 | D11: ='income statement'!D21/'income statement'!D19 -> 0.20433815 | E11: 0.21 | F11: 0.21 | G11: 0.21 | H11: 0.21 | I11: 0.21 | J11: 0.21
B12: current liabilities (% of debt) | C12: ='Balance Sheet'!$D18/'income statement'!C5 -> 0.29782067 | D12: ='Balance Sheet'!$D18/'income statement'!D5 -> 0.29502508 | E12: ='Balance Sheet'!$D18/'income statement'!E5 -> 0.30393242 | F12: =AVERAGE(C12:E12) -> 0.29892606 | G12: =AVERAGE(D12:F12) -> 0.29929452 | H12: =AVERAGE(E12:G12) -> 0.30071767 | I12: =AVERAGE(F12:H12) -> 0.29964608 | J12: =AVERAGE(G12:I12) -> 0.29988609
B13: debt
B14: repayment each year | F14: -2000 | G14: -2000 | H14: -2000 | I14: -2000 | J14: -2000
B15: issuance each year | C15: ='Balance Sheet'!C21-10140 -> 4363 | D15: ='Balance Sheet'!D21-'Balance Sheet'!C21 -> 5129 | E15: ='Balance Sheet'!E21-'Balance Sheet'!D21 -> 3653 | F15: =AVERAGE($C15:$E15) -> 4381.6667 | G15: =AVERAGE($C15:$E15) -> 4381.6667 | H15: =AVERAGE($C15:$E15) -> 4381.6667 | I15: =AVERAGE($C15:$E15) -> 4381.6667 | J15: =AVERAGE($C15:$E15) -> 4381.6667
B16: term loan interest rate
B17: interest rate earned on cash deposit
B22: goodwill | C22: constant
B24: Basic Shares Outstanding | C24: 3174 | D24: 3197 | E24: 3225 | F24: =AVERAGE($C24:$E24) -> 3198.6667 | G24: =AVERAGE($C24:$E24) -> 3198.6667 | H24: =AVERAGE($C24:$E24) -> 3198.6667 | I24: =AVERAGE($C24:$E24) -> 3198.6667 | J24: =AVERAGE($C24:$E24) -> 3198.6667
B25: Shares Outstanding ($mm) | C25: 3485 | D25: 3498 | E25: 3528 | F25: =AVERAGE($C25:$E25) -> 3503.6667 | G25: =AVERAGE($C25:$E25) -> 3503.6667 | H25: =AVERAGE($C25:$E25) -> 3503.6667 | I25: =AVERAGE($C25:$E25) -> 3503.6667 | J25: =AVERAGE($C25:$E25) -> 3503.6667
B26: Net Debt ($mm) | E26: -6800
B28: Net Change In Short-term Investments | C28: -6759 | D28: -7645 | E28: -6951 | F28: =AVERAGE($C28:$E28) -> -7118.3333 | G28: =AVERAGE($C28:$E28) -> -7118.3333 | H28: =AVERAGE($C28:$E28) -> -7118.3333 | I28: =AVERAGE($C28:$E28) -> -7118.3333 | J28: =AVERAGE($C28:$E28) -> -7118.3333
B29: Financial Activities - Other | C29: -227 | D29: -251 | E29: 17 | F29: =AVERAGE(C29:E29) -> -153.66667 | G29: =AVERAGE(D29:F29) -> -129.22222 | H29: =AVERAGE(E29:G29) -> -88.62963 | I29: =AVERAGE(F29:H29) -> -123.83951 | J29: =AVERAGE(G29:I29) -> -113.89712
B31: Stock-Based Compensation | C31: 1812 | D31: 1999 | E31: 2825
B32: Stock-Based Compensation growth | C32: =(C31-1560)/1560 -> 0.16153846 | D32: =(D31-C31)/C31 -> 0.10320088 | E32: =(E31-D31)/D31 -> 0.4132066 | F32: =AVERAGE($C32:$E32) -> 0.22598198 | G32: =AVERAGE($C32:$E32) -> 0.22598198 | H32: =AVERAGE($C32:$E32) -> 0.22598198 | I32: =AVERAGE($C32:$E32) -> 0.22598198 | J32: =AVERAGE($C32:$E32) -> 0.22598198

Sheet income statement
B1: INCOME STATEMENT
F2: ($mm)
B3: Financial Year | C3: 2023A | D3: 2024A | E3: 2025A | F3: 2026E | G3: 2027E | H3: 2028E | I3: 2029E | J3: 2030E
B5: Revenue | C5: 96773 | D5: 97690 | E5: 94827 | F5: =E5*(1+assumptions!F4) -> 101464.89 | G5: =F5*(1+assumptions!G4) -> 109582.08 | H5: =G5*(1+assumptions!H4) -> 119444.47 | I5: =H5*(1+assumptions!I4) -> 131388.92 | J5: =I5*(1+assumptions!J4) -> 145841.7
B6: Cost Of Goods Sold | C6: 79113 | D6: 80240 | E6: 77733 | F6: =F5*assumptions!F5 -> 83154.526 | G6: =G5*assumptions!G5 -> 89806.888 | H6: =H5*assumptions!H5 -> 97889.508 | I6: =I5*assumptions!I5 -> 107678.46 | J6: =J5*assumptions!J5 -> 119523.09
B7: Gross Profit | C7: =C5-C6 -> 17660 | D7: =D5-D6 -> 17450 | E7: =E5-E6 -> 17094 | F7: =F5-F6 -> 18310.364 | G7: =G5-G6 -> 19775.193 | H7: =H5-H6 -> 21554.961 | I7: =I5-I6 -> 23710.457 | J7: =J5-J6 -> 26318.607
B8: Gross Profit Margin % | C8: =C7/C5 -> 0.18248892 | D8: =D7/D5 -> 0.17862627 | E8: =E7/E5 -> 0.18026511 | F8: =F7/F5 -> 0.1804601 | G8: =G7/G5 -> 0.1804601 | H8: =H7/H5 -> 0.1804601 | I8: =I7/I5 -> 0.1804601 | J8: =J7/J5 -> 0.1804601
B10: Research And Development Expenses | C10: 3969 | D10: 4540 | E10: 6411 | F10: =F5*assumptions!F6 -> 5073.2445 | G10: =G5*assumptions!G6 -> 5479.1041 | H10: =H5*assumptions!H6 -> 5972.2234 | I10: =I5*assumptions!I6 -> 6569.4458 | J10: =J5*assumptions!J6 -> 7292.0848
B11: SG&A Expenses | C11: 4800 | D11: 5150 | E11: 5834 | F11: =F6*assumptions!F7 -> 5541.0556 | G11: =G6*assumptions!G7 -> 5984.3401 | H11: =H6*assumptions!H7 -> 6522.9307 | I11: =I6*assumptions!I7 -> 7175.2238 | J11: =J6*assumptions!J7 -> 7964.4984
B12: Other Expense | C12: =C13-SUM(C10:C11) -> 0 | D12: =D13-SUM(D10:D11) -> 684 | E12: =E13-SUM(E10:E11) -> 494 | F12: 0 | G12: 0 | H12: 0 | I12: 0 | J12: 0
B13: Operating Expenses | C13: =C10+C11 -> 8769 | D13: 10374 | E13: 12739 | F13: =SUBTOTAL(109,F10:F12) -> 10614.3 | G13: =SUBTOTAL(109,G10:G12) -> 11463.444 | H13: =SUBTOTAL(109,H10:H12) -> 12495.154 | I13: =SUBTOTAL(109,I10:I12) -> 13744.67 | J13: =SUBTOTAL(109,J10:J12) -> 15256.583
B14: EBIT (Operating Income) | C14: =C7-C13 -> 8891 | D14: =D7-D13 -> 7076 | E14: =E7-E13 -> 4355 | F14: =F7-F13 -> 7696.064 | G14: =G7-G13 -> 8311.7491 | H14: =H7-H13 -> 9059.8066 | I14: =I7-I13 -> 9965.7872 | J14: =J7-J13 -> 11062.024
B15: Depreciation and Amortization | C15: =C17-C14 -> 4667 | D15: =D17-D14 -> 5368 | E15: =E17-E14 -> 6148 | F15: ='Dep Capex Schedule'!F6 -> 5682.3533 | G15: ='Dep Capex Schedule'!G6 -> 6136.9416 | H15: ='Dep Capex Schedule'!H6 -> 6689.2663 | I15: ='Dep Capex Schedule'!I6 -> 7358.193 | J15: ='Dep Capex Schedule'!J6 -> 8167.5942
B17: EBITDA | C17: 13558 | D17: 12444 | E17: 10503 | F17: =F14+F15 -> 13378.417 | G17: =G14+G15 -> 14448.691 | H17: =H14+H15 -> 15749.073 | I17: =I14+I15 -> 17323.98 | J17: =J14+J15 -> 19229.618
B18: Total Non-Operating Income/Expense | C18: 1082 | D18: 1914 | E18: 923 | F18: =AVERAGE($C18:$E18) -> 1306.3333 | G18: =AVERAGE($C18:$E18) -> 1306.3333 | H18: =AVERAGE($C18:$E18) -> 1306.3333 | I18: =AVERAGE($C18:$E18) -> 1306.3333 | J18: =AVERAGE($C18:$E18) -> 1306.3333
B19: Pre-Tax Income (EBT) | C19: =C14+C18 -> 9973 | D19: =D14+D18 -> 8990 | E19: =E14+E18 -> 5278 | F19: =F14+F18 -> 9002.3973 | G19: =G14+G18 -> 9618.0825 | H19: =H14+H18 -> 10366.14 | I19: =I14+I18 -> 11272.121 | J19: =J14+J18 -> 12368.357
B21: Income Taxes | C21: -5001 | D21: 1837 | E21: 1423 | F21: =F19*assumptions!$E11 -> 1890.5034 | G21: =G19*assumptions!$E11 -> 2019.7973 | H21: =H19*assumptions!$E11 -> 2176.8894 | I21: =I19*assumptions!$E11 -> 2367.1453 | J21: =J19*assumptions!$E11 -> 2597.355
B22: Income After Taxes | C22: =C19-C21 -> 14974 | D22: =D19-D21 -> 7153 | E22: =E19-E21 -> 3855 | F22: =F19-F21 -> 7111.8939 | G22: =G19-G21 -> 7598.2851 | H22: =H19-H21 -> 8189.2505 | I22: =I19-I21 -> 8904.9752 | J22: =J19-J21 -> 9771.0021
B23: Income From Discontinued Operations | C23: =C24-C22 -> 23 | D23: =D24-D22 -> -62 | E23: =E24-E22 -> -61
B24: Net Income | C24: 14997 | D24: 7091 | E24: 3794 | F24: =SUM(F22:F23) -> 7111.8939 | G24: =SUM(G22:G23) -> 7598.2851 | H24: =SUM(H22:H23) -> 8189.2505 | I24: =SUM(I22:I23) -> 8904.9752 | J24: =SUM(J22:J23) -> 9771.0021
B26: Basic Shares Outstanding | C26: 3174 | D26: 3197 | E26: 3225 | F26: =assumptions!F24 -> 3198.6667 | G26: =assumptions!G24 -> 3198.6667 | H26: =assumptions!H24 -> 3198.6667 | I26: =assumptions!I24 -> 3198.6667 | J26: =assumptions!J24 -> 3198.6667
B27: Shares Outstanding | C27: 3485 | D27: 3498 | E27: 3528 | F27: =assumptions!F25 -> 3503.6667 | G27: =assumptions!G25 -> 3503.6667 | H27: =assumptions!H25 -> 3503.6667 | I27: =assumptions!I25 -> 3503.6667 | J27: =assumptions!J25 -> 3503.6667
B28: Basic EPS | C28: =C24/C26 -> 4.7249527 | D28: =D24/D26 -> 2.2180169 | E28: =E24/E26 -> 1.1764341 | F28: =F24/F26 -> 2.2233933 | G28: =G24/G26 -> 2.3754539 | H28: =H24/H26 -> 2.5602075 | I28: =I24/I26 -> 2.7839647 | J28: =J24/J26 -> 3.054711
B29: EPS - Earnings Per Share | C29: =C24/C27 -> 4.3032999 | D29: =D24/D27 -> 2.0271584 | E29: =E24/E27 -> 1.0753968 | F29: =F24/F27 -> 2.0298432 | G29: =G24/G27 -> 2.1686667 | H29: =H24/H27 -> 2.3373372 | I29: =I24/I27 -> 2.541616 | J29: =J24/J27 -> 2.7887933

Sheet Balance Sheet
B1: BALANCE SHEET
E2: ($mm)
B3: Financial Year | C3: 2023A | D3: 2024A | E3: 2025A | F3: 2026E | G3: 2027E | H3: 2028E | I3: 2029E | J3: 2030E
B5: Cash On Hand | C5: 29094 | D5: 36563 | E5: 44059 | F5: =E5+'Cash Flow'!F30 -> 54075.841 | G5: =F5+'Cash Flow'!G30 -> 65247.993 | H5: =G5+'Cash Flow'!H30 -> 77844.073 | I5: =H5+'Cash Flow'!I30 -> 92085.965 | J5: =I5+'Cash Flow'!J30 -> 108373.8
B6: Receivables | C6: 3508 | D6: 4418 | E6: 4576 | F6: =E6*(1+assumptions!F4) -> 4896.32 | G6: =F6*(1+assumptions!G4) -> 5288.0256 | H6: =G6*(1+assumptions!H4) -> 5763.9479 | I6: =H6*(1+assumptions!I4) -> 6340.3427 | J6: =I6*(1+assumptions!J4) -> 7037.7804
B7: Inventory | C7: 13626 | D7: 12017 | E7: 12392 | F7: =E7*(1+assumptions!F4) -> 13259.44 | G7: =F7*(1+assumptions!G4) -> 14320.195 | H7: =G7*(1+assumptions!H4) -> 15609.013 | I7: =H7*(1+assumptions!I4) -> 17169.914 | J7: =I7*(1+assumptions!J4) -> 19058.605
B8: Pre-Paid Expenses | C8: 3388 | D8: 5362 | E8: 7615 | F8: =E8*(1+assumptions!F4) -> 8148.05 | G8: =F8*(1+assumptions!G4) -> 8799.894 | H8: =G8*(1+assumptions!H4) -> 9591.8845 | I8: =H8*(1+assumptions!I4) -> 10551.073 | J8: =I8*(1+assumptions!J4) -> 11711.691
B9: Other Current Assets | C9: - | D9: - | E9: - | F9: - | G9: - | H9: - | I9: - | J9: -
B10: Total Current Assets | C10: =SUBTOTAL(109,C5:C9) -> 49616 | D10: =SUBTOTAL(109,D5:D9) -> 58360 | E10: =SUBTOTAL(109,E5:E9) -> 68642 | F10: =SUBTOTAL(109,F5:F9) -> 80379.651 | G10: =SUBTOTAL(109,G5:G9) -> 93656.107 | H10: =SUBTOTAL(109,H5:H9) -> 108808.92 | I10: =SUBTOTAL(109,I5:I9) -> 126147.29 | J10: =SUBTOTAL(109,J5:J9) -> 146181.87
B11: Property, Plant, And Equipment | C11: 29725 | D11: 35836 | E11: 40643 | F11: ='Dep Capex Schedule'!F12 -> 34960.647 | G11: ='Dep Capex Schedule'!G12 -> 28823.705 | H11: ='Dep Capex Schedule'!H12 -> 22134.439 | I11: ='Dep Capex Schedule'!I12 -> 14776.246 | J11: ='Dep Capex Schedule'!J12 -> 6608.6516
B12: Long-Term Investments | C12: - | D12: - | E12: - | F12: - | G12: - | H12: - | I12: - | J12: -
B13: Goodwill And Intangible Assets | C13: 431 | D13: - | E13: - | F13: - | G13: - | H13: - | I13: - | J13: -
B14: Other Long-Term Assets | C14: 9944 | D14: 10609 | E14: 10657 | F14: =E14*(1+assumptions!F7) -> 11367.136 | G14: =F14*(1+assumptions!G7) -> 12124.593 | H14: =G14*(1+assumptions!H7) -> 12932.523 | I14: =H14*(1+assumptions!I7) -> 13794.29 | J14: =I14*(1+assumptions!J7) -> 14713.481
B15: Other / Unspecified Long-Term Assets | C15: =C16-SUM(C11:C14) -> 16902 | D15: =D16-SUM(D11:D14) -> 17265 | E15: =E16-SUM(E11:E14) -> 17864 | F15: =E15*(1+assumptions!F4) -> 19114.48 | G15: =F15*(1+assumptions!G4) -> 20643.638 | H15: =G15*(1+assumptions!H4) -> 22501.566 | I15: =H15*(1+assumptions!I4) -> 24751.722 | J15: =I15*(1+assumptions!J4) -> 27474.412
B16: Total Long-Term Assets | C16: 57002 | D16: 63710 | E16: 69164 | F16: =SUM(F11:F15) -> 65442.263 | G16: =SUM(G11:G15) -> 61591.936 | H16: =SUM(H11:H15) -> 57568.527 | I16: =SUM(I11:I15) -> 53322.258 | J16: =SUM(J11:J15) -> 48796.545
B17: Total Assets | C17: =C10+C16 -> 106618 | D17: =D10+D16 -> 122070 | E17: =E10+E16 -> 137806 | F17: =F10+F16 -> 145821.91 | G17: =G10+G16 -> 155248.04 | H17: =H10+H16 -> 166377.45 | I17: =I10+I16 -> 179469.55 | J17: =J10+J16 -> 194978.42
B18: Total Current Liabilities | C18: 28748 | D18: 28821 | E18: 31714 | F18: ='income statement'!F5*assumptions!F12 -> 30330.5 | G18: ='income statement'!G5*assumptions!G12 -> 32797.316 | H18: ='income statement'!H5*assumptions!H12 -> 35919.062 | I18: ='income statement'!I5*assumptions!I12 -> 39370.174 | J18: ='income statement'!J5*assumptions!J12 -> 43735.896
B19: Long Term Debt | C19: 2857 | D19: 5757 | E19: 6736 | F19: - | G19: - | H19: - | I19: - | J19: -
B20: Other Non-Current Liabilities | C20: 8153 | D20: 10495 | E20: 12860 | F20: - | G20: - | H20: - | I20: - | J20: -
B21: Total Long Term Liabilities | C21: 14503 | D21: 19632 | E21: 23285 | F21: ='Debt Schedule'!F9 -> 25666.667 | G21: 25667 | H21: 25667 | I21: 25667 | J21: 25667
B22: Total Liabilities | C22: =C18+C21 -> 43251 | D22: =D18+D21 -> 48453 | E22: =E18+E21 -> 54999 | F22: =F18+F21 -> 55997.166 | G22: =G18+G21 -> 58464.316 | H22: =H18+H21 -> 61586.062 | I22: =I18+I21 -> 65037.174 | J22: =J18+J21 -> 69402.896
B23: Common Stock Net | C23: 3 | D23: 3 | E23: 3 | F23: 3 | G23: 3 | H23: 3 | I23: 3 | J23: 3
B24: Retained Earnings (Accumulated Deficit) | C24: 27882 | D24: 35209 | E24: 39003 | F24: =E24+'income statement'!F24 -> 46114.894 | G24: =F24+'income statement'!G24 -> 53713.179 | H24: =G24+'income statement'!H24 -> 61902.43 | I24: =H24+'income statement'!I24 -> 70807.405 | J24: =I24+'income statement'!J24 -> 80578.407
B25: Comprehensive Income | C25: -143 | D25: -670 | E25: 361 | F25: 361 | G25: 361 | H25: 361 | I25: 361 | J25: 361
B26: Additional Paid-In Capital | C26: =C28-SUM(C23:C25) -> 35625 | D26: =D28-SUM(D23:D25) -> 39075 | E26: =E28-SUM(E23:E25) -> 43440 | F26: =F17-F22-F23-F24-F25-F27 -> 43345.853 | G26: =G17-G22-G23-G24-G25-G27 -> 42706.548 | H26: =H17-H22-H23-H24-H25-H27 -> 42524.954 | I26: =I17-I22-I23-I24-I25-I27 -> 43260.974 | J26: =J17-J22-J23-J24-J25-J27 -> 44633.114
B27: Other Share Holders Equity | C27: - | D27: - | E27: - | F27: 0 | G27: 0 | H27: 0 | I27: 0 | J27: 0
B28: Share Holder Equity | C28: 63367 | D28: 73617 | E28: 82807 | F28: =SUM(F23:F27) -> 89824.747 | G28: =SUM(G23:G27) -> 96783.727 | H28: =SUM(H23:H27) -> 104791.38 | I28: =SUM(I23:I27) -> 114432.38 | J28: =SUM(J23:J27) -> 125575.52
B29: Total Liabilities And Share Holders Equity | C29: =C22+C28 -> 106618 | D29: =D22+D28 -> 122070 | E29: =E22+E28 -> 137806 | F29: =F22+F28 -> 145821.91 | G29: =G22+G28 -> 155248.04 | H29: =H22+H28 -> 166377.45 | I29: =I22+I28 -> 179469.55 | J29: =J22+J28 -> 194978.42

Sheet Cash Flow
B1: CASH FLOW STATEMENT
E2: ($mm)
B3: Financial Year | C3: 2023A | D3: 2024A | E3: 2025A | F3: 2026E | G3: 2027E | H3: 2028E | I3: 2029E | J3: 2030E
B4: Net Income/Loss | C4: 14974 | D4: 7153 | E4: 3855 | F4: ='income statement'!F24 -> 7111.8939 | G4: ='income statement'!G24 -> 7598.2851 | H4: ='income statement'!H24 -> 8189.2505 | I4: ='income statement'!I24 -> 8904.9752 | J4: ='income statement'!J24 -> 9771.0021
B5: Total Depreciation And Amortization - Cash Flow | C5: 4667 | D5: 5368 | E5: 6148 | F5: ='Dep Capex Schedule'!F6 -> 5682.3533 | G5: ='Dep Capex Schedule'!G6 -> 6136.9416 | H5: ='Dep Capex Schedule'!H6 -> 6689.2663 | I5: ='Dep Capex Schedule'!I6 -> 7358.193 | J5: ='Dep Capex Schedule'!J6 -> 8167.5942
B6: Other Non-Cash Items | C6: -4137 | D6: 2321 | E6: 4102
B7: Total Non-Cash Items | C7: =SUM(C5:C6) -> 530 | D7: =SUM(D5:D6) -> 7689 | E7: =SUM(E5:E6) -> 10250 | F7: =SUM(F5:F6) -> 5682.3533 | G7: =SUM(G5:G6) -> 6136.9416 | H7: =SUM(H5:H6) -> 6689.2663 | I7: =SUM(I5:I6) -> 7358.193 | J7: =SUM(J5:J6) -> 8167.5942
B8: Change In Accounts Receivable | C8: -586 | D8: -1083 | E8: -261 | F8: ='Working Capital Schedule'!E5-'Working Capital Schedule'!F5 -> -320.32 | G8: ='Working Capital Schedule'!F5-'Working Capital Schedule'!G5 -> -391.7056 | H8: ='Working Capital Schedule'!G5-'Working Capital Schedule'!H5 -> -475.9223 | I8: ='Working Capital Schedule'!H5-'Working Capital Schedule'!I5 -> -576.39479 | J8: ='Working Capital Schedule'!I5-'Working Capital Schedule'!J5 -> -697.4377
B9: Change In Inventories | C9: -1195 | D9: 937 | E9: -630 | F9: ='Working Capital Schedule'!E6-'Working Capital Schedule'!F6 -> -867.44 | G9: ='Working Capital Schedule'!F6-'Working Capital Schedule'!G6 -> -1060.7552 | H9: ='Working Capital Schedule'!G6-'Working Capital Schedule'!H6 -> -1288.8176 | I9: ='Working Capital Schedule'!H6-'Working Capital Schedule'!I6 -> -1560.9013 | J9: ='Working Capital Schedule'!I6-'Working Capital Schedule'!J6 -> -1888.6905
B10: Change In Accounts Payable | C10: - | D10: - | E10: - | F10: - | G10: - | H10: - | I10: - | J10: -
B11: Change In Assets/Liabilities | C11: -3072 | D11: -3361 | E11: -2843 | F11: 0 | G11: 0 | H11: 0 | I11: 0 | J11: 0
B12: Total Change In Assets/Liabilities | C12: -2248 | D12: 81 | E12: 642 | F12: =SUBTOTAL(109,F8:F11) -> -1187.76 | G12: =SUBTOTAL(109,G8:G11) -> -1452.4608 | H12: =SUBTOTAL(109,H8:H11) -> -1764.7399 | I12: =SUBTOTAL(109,I8:I11) -> -2137.2961 | J12: =SUBTOTAL(109,J8:J11) -> -2586.1282
B13: Cash Flow From Operating Activities | C13: 13256 | D13: 14923 | E13: 14747 | F13: =F4+F7+F12 -> 11606.487 | G13: =G4+G7+G12 -> 12282.766 | H13: =H4+H7+H12 -> 13113.777 | I13: =I4+I7+I12 -> 14125.872 | J13: =J4+J7+J12 -> 15352.468
B14: Net Change In Property, Plant, And Equipment | C14: -8899 | D14: -11342 | E14: -8527 | F14: ='Dep Capex Schedule'!E12-'Dep Capex Schedule'!F12 -> 5682.3533 | G14: ='Dep Capex Schedule'!F12-'Dep Capex Schedule'!G12 -> 6136.9416 | H14: ='Dep Capex Schedule'!G12-'Dep Capex Schedule'!H12 -> 6689.2663 | I14: ='Dep Capex Schedule'!H12-'Dep Capex Schedule'!I12 -> 7358.193 | J14: ='Dep Capex Schedule'!I12-'Dep Capex Schedule'!J12 -> 8167.5942
B15: Net Change In Intangible Assets | C15: - | D15: - | E15: - | F15: - | G15: - | H15: - | I15: - | J15: -
B16: Net Acquisitions/Divestitures | C16: -64 | D16: - | E16: - | F16: - | G16: - | H16: - | I16: - | J16: -
B17: Net Change In Short-term Investments | C17: -6759 | D17: -7645 | E17: -6951 | F17: =assumptions!F28 -> -7118.3333 | G17: =assumptions!G28 -> -7118.3333 | H17: =assumptions!H28 -> -7118.3333 | I17: =assumptions!I28 -> -7118.3333 | J17: =assumptions!J28 -> -7118.3333
B18: Net Change In Long-Term Investments | C18: 138 | D18: 200 | E18: - | F18: - | G18: - | H18: - | I18: - | J18: -
B19: Net Change In Investments - Total | C19: -6621 | D19: -7445 | E19: -6951 | F19: =SUM(F17:F18) -> -7118.3333 | G19: =SUM(G17:G18) -> -7118.3333 | H19: =SUM(H17:H18) -> -7118.3333 | I19: =SUM(I17:I18) -> -7118.3333 | J19: =SUM(J17:J18) -> -7118.3333
B20: Investing Activities - Other | C20: - | D20: - | E20: - | F20: - | G20: - | H20: - | I20: - | J20: -
B21: Cash Flow From Investing Activities | C21: -15584 | D21: =D14+D19 -> -18787 | E21: =E14+E19 -> -15478 | F21: =F14+F19 -> -1435.98 | G21: =G14+G19 -> -981.39174 | H21: =H14+H19 -> -429.06699 | I21: =I14+I19 -> 239.85964 | J21: =J14+J19 -> 1049.2609
B22: Net Long-Term Debt | C22: 2116 | D22: 2863 | E22: -64 | F22: 0 | G22: 0 | H22: 0 | I22: 0 | J22: 0
B23: Net Current Debt | C23: - | D23: - | E23: - | F23: - | G23: - | H23: - | I23: - | J23: -
B24: Debt Issuance/Retirement Net - Total | C24: =SUM(C22:C23) -> 2116 | D24: =SUM(D22:D23) -> 2863 | E24: =SUM(E22:E23) -> -64 | F24: =SUM(F22:F23) -> 0 | G24: =SUM(G22:G23) -> 0 | H24: =SUM(H22:H23) -> 0 | I24: =SUM(I22:I23) -> 0 | J24: =SUM(J22:J23) -> 0
B25: Net Common Equity Issued/Repurchased | C25: 700 | D25: 1241 | E25: 1186
B26: Net Total Equity Issued/Repurchased | C26: =C25 -> 700 | D26: =D25 -> 1241 | E26: =E25 -> 1186 | F26: =F25 -> 0 | G26: =G25 -> 0 | H26: =H25 -> 0 | I26: =I25 -> 0 | J26: =J25 -> 0
B27: Total Common And Preferred Stock Dividends Paid | C27: - | D27: - | E27: - | F27: - | G27: - | H27: - | I27: - | J27: -
B28: Financial Activities - Other | C28: -227 | D28: -251 | E28: 17 | F28: =assumptions!F29 -> -153.66667 | G28: =assumptions!G29 -> -129.22222 | H28: =assumptions!H29 -> -88.62963 | I28: =assumptions!I29 -> -123.83951 | J28: =assumptions!J29 -> -113.89712
B29: Cash Flow From Financial Activities | C29: =C24+C26+C28 -> 2589 | D29: =D24+D26+D28 -> 3853 | E29: =E24+E26+E28 -> 1139 | F29: =F24+F26+F28 -> -153.66667 | G29: =G24+G26+G28 -> -129.22222 | H29: =H24+H26+H28 -> -88.62963 | I29: =I24+I26+I28 -> -123.83951 | J29: =J24+J26+J28 -> -113.89712
B30: Net Cash Flow | C30: =C13+C21+C29 -> 261 | D30: -152 | E30: 579 | F30: =F13+F21+F29 -> 10016.841 | G30: =G13+G21+G29 -> 11172.152 | H30: =H13+H21+H29 -> 12596.08 | I30: =I13+I21+I29 -> 14241.892 | J30: =J13+J21+J29 -> 16287.832
B31: Stock-Based Compensation | C31: 1812 | D31: 1999 | E31: 2825 | F31: =E31*(1+assumptions!F32) -> 3463.3991 | G31: =F31*(1+assumptions!G32) -> 4246.0649 | H31: =G31*(1+assumptions!H32) -> 5205.5991 | I31: =H31*(1+assumptions!I32) -> 6381.9707 | J31: =I31*(1+assumptions!J32) -> 7824.181
B32: Common Stock Dividends Paid | C32: - | D32: - | E32: - | F32: - | G32: - | H32: - | I32: - | J32: -

Sheet Debt Schedule
B2: Debt and Interest schedule | F2: ($mm)
B3: Financial Year | C3: 2023A | D3: 2024A | E3: 2025A | F3: 2026E | G3: 2027E | H3: 2028E | I3: 2029E | J3: 2030E
B5: Term Loan
B6: Beginning Balance | F6: =E9 -> 23285 | G6: =F9 -> 25666.667 | H6: =G9 -> 28048.333 | I6: =H9 -> 30430 | J6: =I9 -> 32811.667
B7: Issuance | F7: =assumptions!F15 -> 4381.6667 | G7: =assumptions!G15 -> 4381.6667 | H7: =assumptions!H15 -> 4381.6667 | I7: =assumptions!I15 -> 4381.6667 | J7: =assumptions!J15 -> 4381.6667
B8: (Repayment/ Amortization) | F8: =assumptions!F14 -> -2000 | G8: =assumptions!G14 -> -2000 | H8: =assumptions!H14 -> -2000 | I8: =assumptions!I14 -> -2000 | J8: =assumptions!J14 -> -2000
B9: Ending Balance | E9: ='Balance Sheet'!E21 -> 23285 | F9: =SUM(F6:F8) -> 25666.667 | G9: =SUM(G6:G8) -> 28048.333 | H9: =SUM(H6:H8) -> 30430 | I9: =SUM(I6:I8) -> 32811.667 | J9: =SUM(J6:J8) -> 35193.333
B10: Interest Expense Calculation
B11: Average Oustanding
B12: Interest Rate
B13: Interest Expense
B14: Interest Income Calculation
B15: Cash & Cash Equivalents
B16: Effective Cash Interest Rate:
B17: Interest Income

Sheet Dep Capex Schedule
B1: Debt and Interest schedule | F1: ($mm)
B2: Financial Year | C2: 2023A | D2: 2024A | E2: 2025A | F2: 2026E | G2: 2027E | H2: 2028E | I2: 2029E | J2: 2030E
B4: Revenue | C4: ='income statement'!C5 -> 96773 | D4: ='income statement'!D5 -> 97690 | E4: ='income statement'!E5 -> 94827 | F4: ='income statement'!F5 -> 101464.89 | G4: ='income statement'!G5 -> 109582.08 | H4: ='income statement'!H5 -> 119444.47 | I4: ='income statement'!I5 -> 131388.92 | J4: ='income statement'!J5 -> 145841.7
B6: Depreciation | C6: ='income statement'!C15 -> 4667 | D6: ='income statement'!D15 -> 5368 | E6: ='income statement'!E15 -> 6148 | F6: =F4*F7 -> 5682.3533 | G6: =G4*G7 -> 6136.9416 | H6: =H4*H7 -> 6689.2663 | I6: =I4*I7 -> 7358.193 | J6: =J4*J7 -> 8167.5942
B7: Depreciation as % of Revenue | C7: =C6/C4 -> 0.048226261 | D7: =D6/D4 -> 0.05494933 | E7: =E6/E4 -> 0.064833855 | F7: =assumptions!F8 -> 0.056003149 | G7: =assumptions!G8 -> 0.056003149 | H7: =assumptions!H8 -> 0.056003149 | I7: =assumptions!I8 -> 0.056003149 | J7: =assumptions!J8 -> 0.056003149
B9: Beginning PP&E | C9: 23548 | D9: 29725 | E9: 35836 | F9: =E12 -> 40643 | G9: =F12 -> 34960.647 | H9: =G12 -> 28823.705 | I9: =H12 -> 22134.439 | J9: =I12 -> 14776.246
B10: Capital Expenditure | C10: =C12-C9+C11 -> 10844 | D10: =D12-D9+D11 -> 11479 | E10: =E12-E9+E11 -> 10955 | F10: 10146.489 | G10: 10958.208 | H10: 11944.447 | I10: 13138.892 | J10: 14584.17
B11: Depreciation | C11: =C6 -> 4667 | D11: =D6 -> 5368 | E11: =E6 -> 6148 | F11: =F6 -> 5682.3533 | G11: =G6 -> 6136.9416 | H11: =H6 -> 6689.2663 | I11: =I6 -> 7358.193 | J11: =J6 -> 8167.5942
B12: Net PPE | C12: 29725 | D12: 35836 | E12: 40643 | F12: =F9+E16-F11 -> 34960.647 | G12: =G9+F16-G11 -> 28823.705 | H12: =H9+G16-H11 -> 22134.439 | I12: =I9+H16-I11 -> 14776.246 | J12: =J9+I16-J11 -> 6608.6516

Sheet Working Capital Schedule
B1: Debt and Interest schedule | F1: ($mm)
B2: Financial Year | C2: 2023A | D2: 2024A | E2: 2025A | F2: 2026E | G2: 2027E | H2: 2028E | I2: 2029E | J2: 2030E
B4: Working Capital Balances
B5: Accounts Receivables | C5: ='Balance Sheet'!C6 -> 3508 | D5: ='Balance Sheet'!D6 -> 4418 | E5: ='Balance Sheet'!E6 -> 4576 | F5: ='Balance Sheet'!F6 -> 4896.32 | G5: ='Balance Sheet'!G6 -> 5288.0256 | H5: ='Balance Sheet'!H6 -> 5763.9479 | I5: ='Balance Sheet'!I6 -> 6340.3427 | J5: ='Balance Sheet'!J6 -> 7037.7804
B6: Inventory | C6: ='Balance Sheet'!C7 -> 13626 | D6: ='Balance Sheet'!D7 -> 12017 | E6: ='Balance Sheet'!E7 -> 12392 | F6: ='Balance Sheet'!F7 -> 13259.44 | G6: ='Balance Sheet'!G7 -> 14320.195 | H6: ='Balance Sheet'!H7 -> 15609.013 | I6: ='Balance Sheet'!I7 -> 17169.914 | J6: ='Balance Sheet'!J7 -> 19058.605
B9: Total Revenues | C9: ='income statement'!C5 -> 96773 | D9: ='income statement'!D5 -> 97690 | E9: ='income statement'!E5 -> 94827 | F9: ='income statement'!F5 -> 101464.89 | G9: ='income statement'!G5 -> 109582.08 | H9: ='income statement'!H5 -> 119444.47 | I9: ='income statement'!I5 -> 131388.92 | J9: ='income statement'!J5 -> 145841.7
B10: Operating Costs | C10: ='income statement'!C6 -> 79113 | D10: ='income statement'!D6 -> 80240 | E10: ='income statement'!E6 -> 77733 | F10: ='income statement'!F6 -> 83154.526 | G10: ='income statement'!G6 -> 89806.888 | H10: ='income statement'!H6 -> 97889.508 | I10: ='income statement'!I6 -> 107678.46 | J10: ='income statement'!J6 -> 119523.09
B12: Turnover Ratios
B13: Receivables turnover = (Sales / Accounts Receivables) | C13: =C9/C5 -> 27.586374 | D13: =D9/D5 -> 22.111815 | E13: =E9/E5 -> 20.722684 | F13: =F9/F5 -> 20.722684 | G13: =G9/G5 -> 20.722684 | H13: =H9/H5 -> 20.722684 | I13: =I9/I5 -> 20.722684 | J13: =J9/J5 -> 20.722684 | L13: days
B14: Inventory turnover (COGS / Inventory) | C14: =C10/C6 -> 5.8060326 | D14: =D10/D6 -> 6.6772073 | E14: =E10/E6 -> 6.2728373 | F14: =F10/F6 -> 6.2713452 | G14: =G10/G6 -> 6.2713452 | H14: =H10/H6 -> 6.2713452 | I14: =I10/I6 -> 6.2713452 | J14: =J10/J6 -> 6.2713452 | L14: 365
B17: Receivables collection period (365/receivables turnover) | C17: =365/C13 -> 13.23117 | D17: =365/D13 -> 16.507012 | E17: =365/E13 -> 17.613549 | F17: =365/F13 -> 17.613549 | G17: =365/G13 -> 17.613549 | H17: =365/H13 -> 17.613549 | I17: =365/I13 -> 17.613549 | J17: =365/J13 -> 17.613549
B18: Inventory processing period (365/inventory turnover) | C18: =365/C14 -> 62.865648 | D18: =365/D14 -> 54.663572 | E18: =365/E14 -> 58.187385 | F18: =365/F14 -> 58.201229 | G18: =365/G14 -> 58.201229 | H18: =365/H14 -> 58.201229 | I18: =365/I14 -> 58.201229 | J18: =365/J14 -> 58.201229
B20: Cash Collection Cycle | C20: =C17+C18-C19 -> 76.096818 | D20: =D17+D18-D19 -> 71.170584 | E20: =E17+E18-E19 -> 75.800934 | F20: =F17+F18-F19 -> 75.814778 | G20: =G17+G18-G19 -> 75.814778 | H20: =H17+H18-H19 -> 75.814778 | I20: =I17+I18-I19 -> 75.814778 | J20: =J17+J18-J19 -> 75.814778
C30: Increase? | D30: cash outflow
C31: 10 -> 20
C32: =10-20 -> -10 | D32: cash outflow
C34: 10 -> 5 | D34: cash inflows
C35: =10-5 -> 5 | D35: cash inflows
