Workbook

Sheet Cover
B2: Comparable Company Analysis — DLF
B5: Date - February 2026 | FY2025 | Industry - Real Estate | INR crore
B7: NSE: DLF · Source: DLF Annual Reports & Investor Presentations
B9: Valuation Summary Table
D10: Metric | E10: Value
D11: Share Price | E11: ='EV & Multiples Calculation'!B5 -> 573
D12: Implied Price | E12: ='Benchmarking & Target Valuation'!H17 -> 408.57337
D13: Upside / Downside | E13: =(E12/E11)-1 -> -0.28695747
B15: Key Multiples Summary
C16: Multiple | D16: Min | E16: Median | F16: Max | G16: Selected
C17: EV / EBITDA | D17: ='Benchmarking & Target Valuation'!B5 -> 16.938985 | E17: ='Benchmarking & Target Valuation'!E5 -> 32.036449 | F17: ='Benchmarking & Target Valuation'!C5 -> 56.636829 | G17: =E17 -> 32.036449
C18: EV / Revenue | D18: ='Benchmarking & Target Valuation'!B4 -> 3.3714286 | E18: ='Benchmarking & Target Valuation'!E4 -> 10.546008 | F18: ='Benchmarking & Target Valuation'!C4 -> 31.805883 | G18: =E18 -> 10.546008
C19: P / E | D19: ='Benchmarking & Target Valuation'!B6 -> 24.011321 | E19: ='Benchmarking & Target Valuation'!E6 -> 73.519498 | F19: ='Benchmarking & Target Valuation'!C6 -> 287.90107 | G19: N/A

Sheet Assumptions & notes
A1: Assumptions
A3: Key Assumptions Table
A4: Fiscal year used → FY2025
A5: Currency → INR crore
A6: Market data date → February 2026
A7: EV formula definition → EV = Market Cap + Net Debt
A9: Adjustments
A10: EV & Multiples Calculation
A11: EBITDA adjusted where other income inflates operating performance
A12: Sobha Ltd excluded from P/E due to outlier (143x)
A13: Missing data (e.g. Anant Raj pre-sales) excluded
A15: Data Sources
... A20: Notes
A21: 1 | B21: Sobha Lmt. and Brigade Enterprises balance sheet-
B22: Cash includes balances beyond cash equivalents (may include restricted cash)
B23: Real estate earnings may vary due to revenue recognition
A24: 2 | B24: Net Debt = Total Debt – Cash & Cash Equivalents
A25: 3 | B25: Valuation Basis -
B26: Valuation based primarily on EV/EBITDA multiple

Sheet Input
A1: Raw Data Input — Indian Real Estate CCA
A2: (in ₹ crores)
A3: Metric Label | B3: DLF | C3: Oberoi Realty | D3: Prestige Estates | E3: Macrotech (Lodha) | F3: Sobha Ltd | G3: Brigade Enterprises | H3: Anant Raj Ltd
A4: COMPANY INFO
A5: STOCK TICKER | B5: DLF | C5: OBEROIRLTY | D5: PRESTIGE | E5: LODHA | F5: SOBHA | G5: BRIGADE | H5: ANANTRAJ
A6: EXCHANGE | B6: NSE | C6: NSE | D6: NSE | E6: NSE | F6: NSE | G6: NSE | H6: NSE
A7: MARKET DATA
A8: Share Price | B8: 573 | C8: 1470 | D8: 1250 | E8: 869 | F8: 1340 | G8: 650 | H8: 469
A9: Diluted shares Outstanding | B9: 247.53 | C9: 36.36 | D9: 43.07 | E9: 99.76 | F9: 10.69 | G9: 24.44 | H9: 34.33
A10: Equity value/ Market Cap | B10: =B8*B9 -> 141834.69 | C10: =C8*C9 -> 53449.2 | D10: =D8*D9 -> 53837.5 | E10: =E8*E9 -> 86691.44 | F10: =F8*F9 -> 14324.6 | G10: =G8*G9 -> 15886 | H10: =H8*H9 -> 16100.77
A11: CAPITAL STRUCTURE
A12: Total Cash | B12: 2523 | C12: 1003 | D12: 1385 | E12: 1481 | F12: 1699 | G12: 1848 | H12: 267
A13: Total Debt | B13: 3210.47 | C13: 3300 | D13: 3485 | E13: 7542 | F13: 1086 | G13: 1569 | H13: 421
A14: Net Debt | B14: =B13-B12 -> 687.47 | C14: =C13-C12 -> 2297 | D14: =D13-D12 -> 2100 | E14: =E13-E12 -> 6061 | F14: =F13-F12 -> -613 | G14: =G13-G12 -> -279 | H14: =H13-H12 -> 154
A15: Enterprise Value | B15: =B10+B13-B12 -> 142522.16 | C15: =C10+C13-C12 -> 55746.2 | D15: =D10+D13-D12 -> 55937.5 | E15: =E10+E13-E12 -> 92752.44 | F15: =F10+F13-F12 -> 13711.6 | G15: =G10+G13-G12 -> 15607 | H15: =H10+H13-H12 -> 16254.77
A16: INCOME STATEMENT (LTM)
A17: Revenue | B17: 4481 | C17: 5286 | D17: 2873 | E17: 12677 | F17: 4067 | G17: 2117 | H17: 1229
A18: EBITDA | B18: 2787 | C18: 3291 | D18: 1068 | E18: 3804 | F18: 428 | G18: 702 | H18: 287
A19: EBITDA Margin % | B19: =B18/B17 -> 0.62195938 | C19: =C18/C17 -> 0.62258797 | D19: =D18/D17 -> 0.37173686 | E19: =E18/E17 -> 0.30007099 | F19: =F18/F17 -> 0.10523728 | G19: =G18/G17 -> 0.33160132 | H19: =H18/H17 -> 0.23352319
A20: Net Income | B20: 1580 | C20: 2226 | D20: 187 | E20: 2190 | F20: 112 | G20: 455 | H20: 219
A21: EPS | B21: =B20/B9 -> 6.3830647 | C21: =C20/C9 -> 61.221122 | D21: =D20/D9 -> 4.3417692 | E21: =E20/E9 -> 21.952686 | F21: =F20/F9 -> 10.477081 | G21: =G20/G9 -> 18.617021 | H21: =H20/H9 -> 6.3792601
A22: REAL ESTATE SPECIFIC
A23: Pre-sales / Bookings | B23: 21223 | C23: 3437 | D23: 17023 | E23: 17630 | F23: 6277 | G23: 7847 | H23: N/A
A24: collections | B24: 11773 | C24: 2790 | D24: 12084 | E24: 14490 | F24: 6184 | G24: 7250 | H24: N/A
A25: Area Sold (mn sq ft) | B25: 5 | C25: 1.15 | D25: 12.58 | E25: 14.4 | F25: 4.68 | G25: 7.05 | H25: N/A

Sheet EV & Multiples Calculation
A2: Metric Label
A3: COMPANY INFO | B3: DLF | C3: Oberoi Realty | D3: Prestige Estates | E3: Macrotech (Lodha) | F3: Sobha Ltd | G3: Brigade Enterprises | H3: Anant Raj Ltd
A4: ENTERPRISE VALUE
A5: Share Price | B5: =Input!B8 -> 573 | C5: =Input!C8 -> 1470 | D5: =Input!D8 -> 1250 | E5: =Input!E8 -> 869 | F5: =Input!F8 -> 1340 | G5: =Input!G8 -> 650 | H5: =Input!H8 -> 469
A6: Diluted shares Outstanding | B6: =Input!B9 -> 247.53 | C6: =Input!C9 -> 36.36 | D6: =Input!D9 -> 43.07 | E6: =Input!E9 -> 99.76 | F6: =Input!F9 -> 10.69 | G6: =Input!G9 -> 24.44 | H6: =Input!H9 -> 34.33
A7: Equity value/ Market Cap | B7: =Input!B10 -> 141834.69 | C7: =Input!C10 -> 53449.2 | D7: =Input!D10 -> 53837.5 | E7: =Input!E10 -> 86691.44 | F7: =Input!F10 -> 14324.6 | G7: =Input!G10 -> 15886 | H7: =Input!H10 -> 16100.77
A8: CAPITAL STRUCTURE
A9: Total Cash | B9: =Input!B12 -> 2523 | C9: =Input!C12 -> 1003 | D9: =Input!D12 -> 1385 | E9: =Input!E12 -> 1481 | F9: =Input!F12 -> 1699 | G9: =Input!G12 -> 1848 | H9: =Input!H12 -> 267
A10: Total Debt | B10: =Input!B13 -> 3210.47 | C10: =Input!C13 -> 3300 | D10: =Input!D13 -> 3485 | E10: =Input!E13 -> 7542 | F10: =Input!F13 -> 1086 | G10: =Input!G13 -> 1569 | H10: =Input!H13 -> 421
A11: Net Debt | B11: =Input!B14 -> 687.47 | C11: =Input!C14 -> 2297 | D11: =Input!D14 -> 2100 | E11: =Input!E14 -> 6061 | F11: =Input!F14 -> -613 | G11: =Input!G14 -> -279 | H11: =Input!H14 -> 154
A12: Enterprise Value | B12: =Input!B15 -> 142522.16 | C12: =Input!C15 -> 55746.2 | D12: =Input!D15 -> 55937.5 | E12: =Input!E15 -> 92752.44 | F12: =Input!F15 -> 13711.6 | G12: =Input!G15 -> 15607 | H12: =Input!H15 -> 16254.77
A13: INCOME STATEMENT (LTM)
A14: Revenue | B14: =Input!B17 -> 4481 | C14: =Input!C17 -> 5286 | D14: =Input!D17 -> 2873 | E14: =Input!E17 -> 12677 | F14: =Input!F17 -> 4067 | G14: =Input!G17 -> 2117 | H14: =Input!H17 -> 1229
A15: EBITDA | B15: =Input!B18 -> 2787 | C15: =Input!C18 -> 3291 | D15: =Input!D18 -> 1068 | E15: =Input!E18 -> 3804 | F15: =Input!F18 -> 428 | G15: =Input!G18 -> 702 | H15: =Input!H18 -> 287
A16: EBITDA Margin % | B16: =Input!B19 -> 0.62195938 | C16: =Input!C19 -> 0.62258797 | D16: =Input!D19 -> 0.37173686 | E16: =Input!E19 -> 0.30007099 | F16: =Input!F19 -> 0.10523728 | G16: =Input!G19 -> 0.33160132 | H16: =Input!H19 -> 0.23352319
A17: Net Income | B17: =Input!B20 -> 1580 | C17: =Input!C20 -> 2226 | D17: =Input!D20 -> 187 | E17: =Input!E20 -> 2190 | F17: =Input!F20 -> 112 | G17: =Input!G20 -> 455 | H17: =Input!H20 -> 219
A18: EPS | B18: =Input!B21 -> 6.3830647 | C18: =Input!C21 -> 61.221122 | D18: =Input!D21 -> 4.3417692 | E18: =Input!E21 -> 21.952686 | F18: =Input!F21 -> 10.477081 | G18: =Input!G21 -> 18.617021 | H18: =Input!H21 -> 6.3792601
A19: REAL ESTATE SPECIFIC
A20: Pre-sales / Bookings | B20: =Input!B23 -> 21223 | C20: =Input!C23 -> 3437 | D20: =Input!D23 -> 17023 | E20: =Input!E23 -> 17630 | F20: =Input!F23 -> 6277 | G20: =Input!G23 -> 7847 | H20: =Input!H23 -> N/A
A21: collections | B21: =Input!B24 -> 11773 | C21: =Input!C24 -> 2790 | D21: =Input!D24 -> 12084 | E21: =Input!E24 -> 14490 | F21: =Input!F24 -> 6184 | G21: =Input!G24 -> 7250 | H21: =Input!H24 -> N/A
A22: Area Sold (mn sq ft) | B22: =Input!B25 -> 5 | C22: =Input!C25 -> 1.15 | D22: =Input!D25 -> 12.58 | E22: =Input!E25 -> 14.4 | F22: =Input!F25 -> 4.68 | G22: =Input!G25 -> 7.05 | H22: =Input!H25 -> N/A
A23: VALUATION MULTIPLES | J23: MEAN | K23: MEDIAN
A24: EV / Revenue | B24: =B12/B14 -> 31.805883 | C24: =C12/C14 -> 10.546008 | D24: =D12/D14 -> 19.470066 | E24: =E12/E14 -> 7.3165923 | F24: =F12/F14 -> 3.3714286 | G24: =G12/G14 -> 7.3722248 | H24: =H12/H14 -> 13.226013 | J24: =AVERAGE(B24:H24) -> 13.301174 | K24: =MEDIAN(B24:H24) -> 10.546008
A25: EV / EBITDA | B25: =B12/B15 -> 51.138199 | C25: =C12/C15 -> 16.938985 | D25: =D12/D15 -> 52.375936 | E25: =E12/E15 -> 24.382871 | F25: =F12/F15 -> 32.036449 | G25: =G12/G15 -> 22.232194 | H25: =H12/H15 -> 56.636829 | J25: =AVERAGE(B25:H25) -> 36.534495 | K25: =MEDIAN(B25:H25) -> 32.036449
A26: P / E | B26: =B7/B17 -> 89.768791 | C26: =C7/C17 -> 24.011321 | D26: =D7/D17 -> 287.90107 | E26: =E7/E17 -> 39.585132 | F26: =F7/F17 -> 127.89821 | G26: =G7/G17 -> 34.914286 | H26: =H7/H17 -> 73.519498 | J26: =AVERAGE(B26:H26) -> 96.799759 | K26: =MEDIAN(B26:H26) -> 73.519498
A27: P / Pre-sales | B27: =B7/B20 -> 6.6830651 | C27: =C7/C20 -> 15.55112 | D27: =D7/D20 -> 3.1626329 | E27: =E7/E20 -> 4.9172683 | F27: =F7/F20 -> 2.2820774 | G27: =G7/G20 -> 2.0244679 | H27: =Input!H23 -> N/A | J27: =AVERAGE(B27:H27) -> 5.7701053 | K27: =MEDIAN(B27:H27) -> 4.0399506

Sheet Benchmarking & Target Valuation
A2: MULTIPLE BENCHMARKING
A3: MULTIPLE | B3: MIN | C3: MAX | D3: MEAN | E3: MEDIAN | F3: TRIMMED MEAN
A4: ='EV & Multiples Calculation'!A24 -> EV / Revenue | B4: =MIN('EV & Multiples Calculation'!B24:H24) -> 3.3714286 | C4: =MAX('EV & Multiples Calculation'!B24:H24) -> 31.805883 | D4: ='EV & Multiples Calculation'!J24 -> 13.301174 | E4: ='EV & Multiples Calculation'!K24 -> 10.546008 | F4: =TRIMMEAN('EV & Multiples Calculation'!B24:H24, 0.2) -> 13.301174
A5: ='EV & Multiples Calculation'!A25 -> EV / EBITDA | B5: =MIN('EV & Multiples Calculation'!B25:H25) -> 16.938985 | C5: =MAX('EV & Multiples Calculation'!B25:H25) -> 56.636829 | D5: ='EV & Multiples Calculation'!J25 -> 36.534495 | E5: ='EV & Multiples Calculation'!K25 -> 32.036449 | F5: =TRIMMEAN('EV & Multiples Calculation'!B25:H25, 0.2) -> 36.534495
A6: ='EV & Multiples Calculation'!A26 -> P / E | B6: =MIN('EV & Multiples Calculation'!B26:H26) -> 24.011321 | C6: =MAX('EV & Multiples Calculation'!B26:H26) -> 287.90107 | D6: ='EV & Multiples Calculation'!J26 -> 96.799759 | E6: ='EV & Multiples Calculation'!K26 -> 73.519498 | F6: =TRIMMEAN('EV & Multiples Calculation'!B26:H26, 0.2) -> 96.799759
A7: ='EV & Multiples Calculation'!A27 -> P / Pre-sales | B7: =MIN('EV & Multiples Calculation'!B27:H27) -> 2.0244679 | C7: =MAX('EV & Multiples Calculation'!B27:H27) -> 15.55112 | D7: ='EV & Multiples Calculation'!J27 -> 5.7701053 | E7: ='EV & Multiples Calculation'!K27 -> 4.0399506 | F7: =TRIMMEAN('EV & Multiples Calculation'!B27:H27, 0.2) -> 5.7701053
A10: OUTLIER EXCLUSIONS | B10: DLF excluded from EV/EBITDA trimmed mean —Other Income distortion
B11: Sobha P/E of 143x excluded — margin compression outlier
B12: Anant Raj excluded from P/Pre-sales — metric not disclosed
A14: IMPLIED VALUATION
A15: MULTIPLE USED | B15: TRIMMED MEAN | C15: METRIC (₹ CR) | D15: IMPLIED EV / MKT CAP | E15: NET DEBT | F15: IMPLIED EQUITY VALUE | G15: SHARES (CR) | H15: IMPLIED SHARE PRICE | I15: CURRENT PRICE | J15: UPSIDE / DOWNSIDE %
A16: EV / REVENUE | B16: =F4 -> 13.301174 | C16: ='EV & Multiples Calculation'!B14 -> 4481 | D16: =B16*C16 -> 59602.559 | E16: ='EV & Multiples Calculation'!B11 -> 687.47 | F16: =D16-E16 -> 58915.089 | G16: ='EV & Multiples Calculation'!B6 -> 247.53 | H16: =F16/G16 -> 238.01191 | I16: =Input!B8 -> 573 | J16: =(H16-I16)/I16 -> -0.58462144
A17: =A5 -> EV / EBITDA | B17: =F5 -> 36.534495 | C17: ='EV & Multiples Calculation'!B15 -> 2787 | D17: =B17*C17 -> 101821.64 | E17: =E16 -> 687.47 | F17: =D17-E17 -> 101134.17 | G17: =G16 -> 247.53 | H17: =F17/G17 -> 408.57337 | I17: =I16 -> 573 | J17: =(H17-I17)/I17 -> -0.28695747
A18: =A6 -> P / E | B18: =F6 -> 96.799759 | C18: ='EV & Multiples Calculation'!B17 -> 1580 | D18: =B18*C18 -> 152943.62 | E18: NA | F18: =D18 -> 152943.62 | G18: =G17 -> 247.53 | H18: =F18/G18 -> 617.87912 | I18: =I17 -> 573 | J18: =(H18-I18)/I18 -> 0.078323074
A19: =A7 -> P / Pre-sales | B19: =F7 -> 5.7701053 | C19: ='EV & Multiples Calculation'!B20 -> 21223 | D19: =B19*C19 -> 122458.94 | E19: NA | F19: =D19 -> 122458.94 | G19: =G18 -> 247.53 | H19: =F19/G19 -> 494.72365 | I19: =I18 -> 573 | J19: =(H19-I19)/I19 -> -0.13660794

Sheet Football Field Chart
A1: Football Field — Implied Equity Value Analysis
A2: Indian Real Estate | FY2025 Actuals | ₹ Crore
A3: Subject Company: DLF
A4: As of: March 2026
A6: COMPANY MULTIPLES | B6: EV/REVENUE | C6: EV/EBITDA | D6: P/E | E6: P/PRE-SALES
A7: ='EV & Multiples Calculation'!C3 -> Oberoi Realty | B7: ='EV & Multiples Calculation'!C24 -> 10.546008 | C7: ='EV & Multiples Calculation'!C25 -> 16.938985 | D7: ='EV & Multiples Calculation'!C26 -> 24.011321 | E7: ='EV & Multiples Calculation'!C27 -> 15.55112
A8: ='EV & Multiples Calculation'!D3 -> Prestige Estates | B8: ='EV & Multiples Calculation'!D24 -> 19.470066 | C8: ='EV & Multiples Calculation'!D25 -> 52.375936 | D8: ='EV & Multiples Calculation'!D26 -> 287.90107 | E8: ='EV & Multiples Calculation'!D27 -> 3.1626329
A9: ='EV & Multiples Calculation'!E3 -> Macrotech (Lodha) | B9: ='EV & Multiples Calculation'!E24 -> 7.3165923 | C9: ='EV & Multiples Calculation'!E25 -> 24.382871 | D9: ='EV & Multiples Calculation'!E26 -> 39.585132 | E9: ='EV & Multiples Calculation'!E27 -> 4.9172683
A10: ='EV & Multiples Calculation'!F3 -> Sobha Ltd | B10: ='EV & Multiples Calculation'!F24 -> 3.3714286 | C10: ='EV & Multiples Calculation'!F25 -> 32.036449 | D10: ='EV & Multiples Calculation'!F26 -> 127.89821 | E10: ='EV & Multiples Calculation'!F27 -> 2.2820774
A11: ='EV & Multiples Calculation'!G3 -> Brigade Enterprises | B11: ='EV & Multiples Calculation'!G24 -> 7.3722248 | C11: ='EV & Multiples Calculation'!G25 -> 22.232194 | D11: ='EV & Multiples Calculation'!G26 -> 34.914286 | E11: ='EV & Multiples Calculation'!G27 -> 2.0244679
A12: ='EV & Multiples Calculation'!H3 -> Anant Raj Ltd | B12: ='EV & Multiples Calculation'!H24 -> 13.226013 | C12: ='EV & Multiples Calculation'!H25 -> 56.636829 | D12: ='EV & Multiples Calculation'!H26 -> 73.519498 | E12: ='EV & Multiples Calculation'!H27 -> N/A
A14: STATISTICS | B14: EV/REVENUE | C14: EV/EBITDA | D14: P/E | E14: P/PRE-SALES
A15: MINIMUM | B15: =MIN(B7:B12) -> 3.3714286 | C15: =MIN(C7:C12) -> 16.938985 | D15: =MIN(D7:D12) -> 24.011321 | E15: =MIN(E7:E12) -> 2.0244679
A16: 25TH PERCENTILE | B16: =PERCENTILE(B7:B12,0.25) -> 7.3305004 | C16: =PERCENTILE(C7:C12,0.25) -> 22.769863 | D16: =PERCENTILE(D7:D12,0.25) -> 36.081997 | E16: =PERCENTILE(E7:E12,0.25) -> 2.2820774
A17: MEDIAN | B17: =MEDIAN(B7:B12) -> 8.9591166 | C17: =MEDIAN(C7:C12) -> 28.20966 | D17: =MEDIAN(D7:D12) -> 56.552315 | E17: =MEDIAN(E7:E12) -> 3.1626329
A18: 75TH PERCENTILE | B18: =PERCENTILE(B7:B12,0.75) -> 12.556012 | C18: =PERCENTILE(C7:C12,0.75) -> 47.291064 | D18: =PERCENTILE(D7:D12,0.75) -> 114.30354 | E18: =PERCENTILE(E7:E12,0.75) -> 4.9172683
A19: MAXIMUM | B19: =MAX(B7:B12) -> 19.470066 | C19: =MAX(C7:C12) -> 56.636829 | D19: =MAX(D7:D12) -> 287.90107 | E19: =MAX(E7:E12) -> 15.55112
A20: NO. OF COMPS (n) | B20: 7
A22: IMPLIED EQUITY VALUE — DLF | B22: EV/REVENUE | C22: EV/EBITDA | D22: P/E | E22: P/PRE-SALES | G22: DLF | H22: IN (₹Cr)
A23: MINIMUM IMPLIED | B23: =B15*$H$23-$H$27 -> 14419.901 | C23: =C15*$H$24-$H$27 -> 46521.482 | D23: =D15*$H$25 -> 37937.887 | E23: =E15*$H$26 -> 42965.283 | G23: REVENUE | H23: =Input!B17 -> 4481
A24: 25TH PERCENTILE IMPLIED | B24: =B16*$H$23-$H$27 -> 32160.502 | C24: =C16*$H$24-$H$27 -> 62772.138 | D24: =D16*$H$25 -> 57009.556 | E24: =E16*$H$26 -> 48432.529 | G24: EBITDA | H24: =Input!B18 -> 2787
A25: MEDIAN IMPLIED | B25: =B17*$H$23-$H$27 -> 39458.331 | C25: =C17*$H$24-$H$27 -> 77932.851 | D25: =D17*$H$25 -> 89352.658 | E25: =E17*$H$26 -> 67120.558 | G25: NET INCOME | H25: =Input!B20 -> 1580
A26: 75TH PERCENTILE IMPLIED | B26: =B18*$H$23-$H$27 -> 55576.019 | C26: =C18*$H$24-$H$27 -> 131112.73 | D26: =D18*$H$25 -> 180599.59 | E26: =E18*$H$26 -> 104359.18 | G26: PRE-SALES | H26: =Input!B23 -> 21223
A27: MAXIMUM IMPLIED | B27: =B19*$H$23-$H$27 -> 86557.896 | C27: =C19*$H$24-$H$27 -> 157159.37 | D27: =D19*$H$25 -> 454883.69 | E27: =E19*$H$26 -> 330041.42 | G27: NET DEBT | H27: =Input!B14 -> 687.47
A28: CHART STAGING TABLE
A29: METHOD | B29: Invisible Base (₹ Cr) | C29: Lower whisker (Min→P25) | D29: IQR box (P25→P75) | E29: Upper whisker (P75→Max) | F29: Current Mkt Cap | G29: Median implied
A30: EV/REVENUE | B30: =B23 -> 14419.901 | C30: =B24-B23 -> 17740.601 | D30: =B26-B24 -> 23415.517 | E30: =B27-B26 -> 30981.877 | F30: =Input!B10 -> 141834.69 | G30: =B25 -> 39458.331
A31: EV/EBITDA | B31: =C23 -> 46521.482 | C31: =C24-C23 -> 16250.657 | D31: =C26-C24 -> 68340.588 | E31: =C27-C26 -> 26046.647 | F31: =Input!B10 -> 141834.69 | G31: =C25 -> 77932.851
A32: P/E | B32: =D23 -> 37937.887 | C32: =D24-D23 -> 19071.669 | D32: =D26-D24 -> 123590.03 | E32: =D27-D26 -> 274284.1 | F32: =Input!B10 -> 141834.69 | G32: =D25 -> 89352.658
A33: P/PRE-SALES | B33: =E23 -> 42965.283 | C33: =E24-E23 -> 5467.2459 | D33: =E26-E24 -> 55926.656 | E33: =E27-E26 -> 225682.24 | F33: =Input!B10 -> 141834.69 | G33: =E25 -> 67120.558
A50: Notes: 1. P/E excludes companies with P/E > 250x (distorted by low base year earnings) 2. EV/EBITDA excludes DLF Properties — EBITDA margins distorted by large Other Income 3. P/Pre-sales based on 6 comps — Anant Raj excluded (pre-sales not disclosed in investor PPT). 4. All figures FY2025. Share prices as of dec 2025. Source: BSE filings, investor presentations. 5. Net Debt = Total Debt − Total Cash & Equivalents

Sheet RE Schedules
A1: Real Estate Operating Schedules
A2: Indian Real Estate | FY2025 | ₹ Crore unless stated
A3: Source: BSE Filings, Investor Presentations
A5: METRIC | B5: DLF | C5: Oberoi Realty | D5: Prestige Estates | E5: Macrotech (Lodha) | F5: Sobha Ltd | G5: Brigade Enterprises | H5: Anant Raj Ltd
A6: PRE-SALES & COLLECTIONS TRACKER
A7: Pre-sales / Bookings (₹ Cr) | B7: =Input!B23 -> 21223 | C7: =Input!C23 -> 3437 | D7: =Input!D23 -> 17023 | E7: =Input!E23 -> 17630 | F7: =Input!F23 -> 6277 | G7: =Input!G23 -> 7847 | H7: =Input!H23 -> N/A
A8: Pre-sales / Bookings of FY2024( ₹ Cr) | B8: 14778 | C8: 4007 | D8: 21040 | E8: 14520 | F8: 6644 | G8: 6013 | H8: =Input!H24 -> N/A
A9: YoY Growth % | B9: =(B7-B8)/B8 -> 0.43612126 | C9: =(C7-C8)/C8 -> -0.14225106 | D9: =(D7-D8)/D8 -> -0.19092205 | E9: =(E7-E8)/E8 -> 0.21418733 | F9: =(F7-F8)/F8 -> -0.055237809 | G9: =(G7-G8)/G8 -> 0.30500582 | H9: N/A
A10: Collections (₹ Cr) | B10: =Input!B24 -> 11773 | C10: =Input!C24 -> 2790 | D10: =Input!D24 -> 12084 | E10: =Input!E24 -> 14490 | F10: =Input!F24 -> 6184 | G10: =Input!G24 -> 7250 | H10: =IF(H7="N/A","—",H10/H7) -> —
A11: Area Sold (mn sq ft) | B11: =Input!B25 -> 5 | C11: =Input!C25 -> 1.15 | D11: =Input!D25 -> 12.58 | E11: =Input!E25 -> 14.4 | F11: =Input!F25 -> 4.68 | G11: =Input!G25 -> 7.05 | H11: =Input!H25 -> N/A
A12: Average Realization (₹ per sq ft) | B12: =IF(B11>0, (B7*10000000)/(B11*1000000), "—") -> 42446 | C12: =IF(C11>0, (C7*10000000)/(C11*1000000), "—") -> 29886.957 | D12: =IF(D11>0, (D7*10000000)/(D11*1000000), "—") -> 13531.797 | E12: =IF(E11>0, (E7*10000000)/(E11*1000000), "—") -> 12243.056 | F12: =IF(F11>0, (F7*10000000)/(F11*1000000), "—") -> 13412.393 | G12: =IF(G11>0, (G7*10000000)/(G11*1000000), "—") -> 11130.496 | H12: {=IF(ISNUMBER(_xleta.CELL), formula, "—")} -> —
A13: Pre-sales / Market Cap (x) | B13: =IF(B7>0, B7/Input!B10, "—") -> 0.14963194 | C13: =IF(C7>0, C7/Input!C10, "—") -> 0.064304049 | D13: =IF(D7>0, D7/Input!D10, "—") -> 0.31619225 | E13: =IF(E7>0, E7/Input!E10, "—") -> 0.20336495 | F13: =IF(F7>0, F7/Input!F10, "—") -> 0.43819723 | G13: =IF(G7>0, G7/Input!G10, "—") -> 0.49395694 | H13: {=IF(ISNUMBER(_xleta.CELL), formula, "—")} -> —
A14: Pre-sales / EV (x) | B14: =B7/Input!B15 -> 0.14891018 | C14: =C7/Input!C15 -> 0.061654427 | D14: =D7/Input!D15 -> 0.30432179 | E14: =E7/Input!E15 -> 0.19007586 | F14: =F7/Input!F15 -> 0.45778757 | G14: =G7/Input!G15 -> 0.50278721 | H14: =IF(H7="N/A","—",H7/Input!H15) -> —
A15: Collections / Pre-sales (%) | B15: =B10/B7 -> 0.55472836 | C15: =C10/C7 -> 0.81175444 | D15: =D10/D7 -> 0.70986313 | E15: =E10/E7 -> 0.8218945 | F15: =F10/F7 -> 0.98518401 | G15: =G10/G7 -> 0.92391997 | H15: {=IF(ISNUMBER(_xleta.CELL), formula, "—")} -> —
A16: Pre-sales Rank | B16: =IF(B7>0, RANK(B7, $B$7:$H$7, 0), "—") -> 1 | C16: =IF(C7>0, RANK(C7, $B$7:$H$7, 0), "—") -> 6 | D16: =IF(D7>0, RANK(D7, $B$7:$H$7, 0), "—") -> 3 | E16: =IF(E7>0, RANK(E7, $B$7:$H$7, 0), "—") -> 2 | F16: =IF(F7>0, RANK(F7, $B$7:$H$7, 0), "—") -> 5 | G16: =IF(G7>0, RANK(G7, $B$7:$H$7, 0), "—") -> 4 | H16: {=IF(ISNUMBER(_xleta.CELL), formula, "—")} -> —
A17: Area Sold Rank | B17: =IF(B11>0, RANK(B11, $B$11:$H$11, 0), "—") -> 4 | C17: =IF(C11>0, RANK(C11, $B$11:$H$11, 0), "—") -> 6 | D17: =IF(D11>0, RANK(D11, $B$11:$H$11, 0), "—") -> 2 | E17: =IF(E11>0, RANK(E11, $B$11:$H$11, 0), "—") -> 1 | F17: =IF(F11>0, RANK(F11, $B$11:$H$11, 0), "—") -> 5 | G17: =IF(G11>0, RANK(G11, $B$11:$H$11, 0), "—") -> 3 | H17: {=IF(ISNUMBER(_xleta.CELL), formula, "—")} -> —
